<?xml version="1.0" encoding="Windows-1252"?>
<ItemDatabase xmlns:xsi="http://www.w3.org/2001/XMLSchema-instance" xmlns:xsd="http://www.w3.org/2001/XMLSchema">
  <CombatEquipment>
    <ItemEntry>
      <name>Helmet of Truth</name>
      <quality>Common</quality>
      <type>Head</type>
      <strength>1</strength>
      <intelligence>2</intelligence>
      <vitality>3</vitality>
    </ItemEntry>
    <ItemEntry>
      <name>Chest of Whatever</name>
      <quality>Rare</quality>
      <type>Chest</type>
      <strength>3</strength>
      <intelligence>0</intelligence>
      <vitality>3</vitality>
    </ItemEntry>
  </CombatEquipment>
</ItemDatabase>